pyautostart.py
pyautostart-0.1.2.dist-info/LICENSE
pyautostart-0.1.2.dist-info/METADATA
pyautostart-0.1.2.dist-info/WHEEL
pyautostart-0.1.2.dist-info/top_level.txt
pyautostart-0.1.2.dist-info/RECORD
